geosoupML/__init__.py
geosoupML/distance.py
geosoupML/regression.py
geosoupML/samples.py
geosoupML/spatial.py
geosoupML-0.1.56.dist-info/DESCRIPTION.rst
geosoupML-0.1.56.dist-info/METADATA
geosoupML-0.1.56.dist-info/RECORD
geosoupML-0.1.56.dist-info/WHEEL
geosoupML-0.1.56.dist-info/metadata.json
geosoupML-0.1.56.dist-info/top_level.txt
