Metadata-Version: 2.0
Name: geosoupML
Version: 0.1.56
Summary: Machine Learning support for geosoup
Home-page: https://github.com/masseyr/geosoupML
Author: Richard Massey
Author-email: rm885@nau.edu
License: Apache License 2.0
Keywords: geospatial raster vector global spatial regression hierarchical samples random
Platform: UNKNOWN
Classifier: Topic :: Scientific/Engineering :: GIS
Classifier: Intended Audience :: Science/Research
Classifier: Operating System :: OS Independent
Classifier: Programming Language :: Python
Classifier: Programming Language :: Python :: 2
Classifier: Programming Language :: Python :: 2.7
Classifier: Programming Language :: Python :: 3
Classifier: Programming Language :: Python :: 3.6
Classifier: Programming Language :: Python :: 3.7
Classifier: Programming Language :: Python :: 3.8
Requires-Dist: geosoup
Requires-Dist: h5py
Requires-Dist: numpy
Requires-Dist: psutil
Requires-Dist: scikit-learn
Requires-Dist: scipy
